storey/__init__.py
storey/aggregation_utils.py
storey/aggregations.py
storey/dataframe.py
storey/drivers.py
storey/dtypes.py
storey/flow.py
storey/queue.py
storey/redis_driver.py
storey/sources.py
storey/sql_driver.py
storey/table.py
storey/targets.py
storey/timescaledb_target.py
storey/utils.py
storey/windowed_store.py
storey/steps/__init__.py
storey/steps/assertion.py
storey/steps/collector.py
storey/steps/flatten.py
storey/steps/foreach.py
storey/steps/partition.py
storey/steps/sample.py
storey/transformations/__init__.py
storey-1.11.11.dist-info/licenses/LICENSE
storey-1.11.11.dist-info/METADATA
storey-1.11.11.dist-info/WHEEL
storey-1.11.11.dist-info/top_level.txt
storey-1.11.11.dist-info/RECORD
