Metadata-Version: 2.4
Name: storey
Version: 1.11.11
Summary: Async flows
Home-page: https://github.com/mlrun/storey
Author: Iguazio
Author-email: yaronh@iguazio.com
License: Apache
Classifier: Development Status :: 4 - Beta
Classifier: Intended Audience :: Developers
Classifier: License :: OSI Approved :: Apache Software License
Classifier: Operating System :: POSIX :: Linux
Classifier: Operating System :: Microsoft :: Windows
Classifier: Operating System :: MacOS
Classifier: Programming Language :: Python :: 3
Classifier: Programming Language :: Python :: 3.11
Classifier: Programming Language :: Python
Classifier: Topic :: Software Development :: Libraries :: Python Modules
Classifier: Topic :: Software Development :: Libraries
Requires-Python: >=3.11
License-File: LICENSE
Requires-Dist: aiohttp~=3.8
Requires-Dist: v3io<0.8,>=0.6.10
Requires-Dist: pandas!=1.5.*,<2.2,>=1
Requires-Dist: numpy<1.27,>=1.16.5
Requires-Dist: pyarrow<18,>=1
Requires-Dist: v3io-frames!=0.11.*,!=0.12.*,>=0.10.14
Requires-Dist: fsspec>=0.6.2
Requires-Dist: v3iofs~=0.1.17
Requires-Dist: xxhash>=1
Requires-Dist: nuclio-sdk>=0.5.3
Provides-Extra: kafka
Requires-Dist: kafka-python~=2.0; extra == "kafka"
Provides-Extra: redis
Requires-Dist: redis~=4.3; extra == "redis"
Provides-Extra: sqlalchemy
Requires-Dist: sqlalchemy~=1.3; extra == "sqlalchemy"
Provides-Extra: psycopg
Requires-Dist: psycopg[binary,pool]~=3.2; extra == "psycopg"
Dynamic: author
Dynamic: author-email
Dynamic: classifier
Dynamic: description
Dynamic: description-content-type
Dynamic: home-page
Dynamic: license
Dynamic: license-file
Dynamic: provides-extra
Dynamic: requires-dist
Dynamic: requires-python
Dynamic: summary
